{
	"season": 2022,
	"events": [{
		"id": 1,
		"axware_id": 13968,
		"status": "active",
		"axware_host": "SASCA",
		"results_filename": "e01-jan29",
		"site_host": "SASCA",
		"joint": "false",
		"site": "RCCC",
		"date": "20220129",
		"venue": "River City Community Church",
		"address": "16765 Lookout Rd, Schertz, TX 78154",
		"map_url": "https://goo.gl/maps/8TCVryDTjQU2"
	},
	{
		"id": 2,
		"axware_id": 13969,
		"status": "active",
		"axware_host": "SASCA",
		"results_filename": "e02-feb12",
		"site_host": "SASCA",
		"joint": "false",
		"site": "RCCC",
		"date": "20220212",
		"venue": "River City Community Church",
		"address": "16765 Lookout Rd, Schertz, TX 78154",
		"map_url": "https://goo.gl/maps/8TCVryDTjQU2"
	},
	{
		"id": 3,
		"axware_id": 13970,
		"status": "active",
		"axware_host": "SASCA",
		"results_filename": "e03-mar12",
		"site_host": "SASCA",
		"joint": "false",
		"site": "RCCC",
		"date": "20220312",
		"venue": "River City Community Church",
		"address": "16765 Lookout Rd, Schertz, TX 78154",
		"map_url": "https://goo.gl/maps/8TCVryDTjQU2"
	},
	{
		"id": 4,
		"axware_id": 0,
		"status": "active",
		"axware_host": "Spokes",
		"results_filename": "e04-mar26",
		"site_host": "Spokes",
		"joint": "true",
		"site": "RCCC",
		"date": "20220326",
		"venue": "River City Community Church",
		"address": "16765 Lookout Rd, Schertz, TX 78154",
		"map_url": "https://goo.gl/maps/8TCVryDTjQU2"
	},
	{
		"id": 5,
		"axware_id": 13971,
		"status": "active",
		"axware_host": "SASCA",
		"results_filename": "e05-may14",
		"site_host": "SASCA",
		"joint": "false",
		"site": "RCCC",
		"date": "20220514",
		"venue": "River City Community Church",
		"address": "16765 Lookout Rd, Schertz, TX 78154",
		"map_url": "https://goo.gl/maps/8TCVryDTjQU2"
	},
	{
		"id": 6,
		"axware_id": 13972,
		"status": "active",
		"axware_host": "SASCA",
		"results_filename": "e06-jun11",
		"site_host": "SASCA",
		"joint": "true",
		"site": "RCCC",
		"date": "20220611",
		"venue": "River City Community Church",
		"address": "16765 Lookout Rd, Schertz, TX 78154",
		"map_url": "https://goo.gl/maps/8TCVryDTjQU2"
	},
	{
		"id": 7,
		"axware_id": 13973,
		"status": "active",
		"axware_host": "SASCA",
		"results_filename": "e07-jun25",
		"site_host": "SASCA",
		"joint": "false",
		"site": "RCCC",
		"date": "20220625",
		"venue": "River City Community Church",
		"address": "16765 Lookout Rd, Schertz, TX 78154",
		"map_url": "https://goo.gl/maps/8TCVryDTjQU2"
	},
	{
		"id": 8,
		"axware_id": 13974,
		"status": "active",
		"axware_host": "SASCA",
		"results_filename": "e08-jul09",
		"site_host": "SASCA",
		"joint": "false",
		"site": "RCCC",
		"date": "20220709",
		"venue": "River City Community Church",
		"address": "16765 Lookout Rd, Schertz, TX 78154",
		"map_url": "https://goo.gl/maps/8TCVryDTjQU2"
	},
	{
		"id": 9,
		"axware_id": 13975,
		"status": "active",
		"axware_host": "SASCA",
		"results_filename": "e09-jul23",
		"site_host": "SASCA",
		"joint": "false",
		"site": "RCCC",
		"date": "20220723",
		"venue": "River City Community Church",
		"address": "16765 Lookout Rd, Schertz, TX 78154",
		"map_url": "https://goo.gl/maps/8TCVryDTjQU2"
	},
	{
		"id": 10,
		"axware_id": 13976,
		"status": "active",
		"axware_host": "SASCA",
		"results_filename": "e10-sep24",
		"site_host": "SASCA",
		"joint": "false",
		"site": "RCCC",
		"date": "20220924",
		"venue": "River City Community Church",
		"address": "16765 Lookout Rd, Schertz, TX 78154",
		"map_url": "https://goo.gl/maps/8TCVryDTjQU2"
	},
	{
		"id": 11,
		"axware_id": 13977,
		"status": "active",
		"axware_host": "SASCA",
		"results_filename": "e10-nov12",
		"site_host": "SASCA",
		"joint": "false",
		"site": "RCCC",
		"date": "20221112",
		"venue": "River City Community Church",
		"address": "16765 Lookout Rd, Schertz, TX 78154",
		"map_url": "https://goo.gl/maps/8TCVryDTjQU2"
	},
	{
		"id": 12,
		"axware_id": 13978,
		"status": "active",
		"axware_host": "SASCA",
		"results_filename": "e12-dec10",
		"site_host": "SASCA",
		"joint": "false",
		"site": "RCCC",
		"date": "20221210",
		"venue": "River City Community Church",
		"address": "16765 Lookout Rd, Schertz, TX 78154",
		"map_url": "https://goo.gl/maps/8TCVryDTjQU2"
	}],
	"meetings": [
		{
		"id": 1,
	    "event_id": 1,
		"status": "active",
	    "date": "20220202",
		"venue": "Online",
	    "address": "Zoom",
	    "map_url": ""
		},
	  {
		"id": 2,
	    "event_id": 2,
		"status": "active",
	    "date": "20220216",
		"venue": "Longhorn Cafe",
		"address": "1003 Rittiman Rd, San Antonio, TX 78218",
		"map_url": "https://goo.gl/maps/3WWg1pXmNQA2"
		},
	  {
		"id": 3,
	    "event_id": 3,
		"status": "active",
	    "date": "20220316",
		"venue": "Longhorn Cafe",
		"address": "1003 Rittiman Rd, San Antonio, TX 78218",
		"map_url": "https://goo.gl/maps/3WWg1pXmNQA2"
		},
	  {
		"id": 4,
	    "event_id": 4,
		"status": "active",
	    "date": "20220330",
		"venue": "Longhorn Cafe",
		"address": "1003 Rittiman Rd, San Antonio, TX 78218",
		"map_url": "https://goo.gl/maps/3WWg1pXmNQA2"
		},
	  {
		"id": 5,
	    "event_id": 5,
		"status": "active",
	    "date": "20220518",
		"venue": "Longhorn Cafe",
		"address": "1003 Rittiman Rd, San Antonio, TX 78218",
		"map_url": "https://goo.gl/maps/3WWg1pXmNQA2"
		},
	  {
		"id": 6,
	    "event_id": 6,
		"status": "active",
	    "date": "20220615",
		"venue": "Longhorn Cafe",
		"address": "1003 Rittiman Rd, San Antonio, TX 78218",
		"map_url": "https://goo.gl/maps/3WWg1pXmNQA2"
		},
	  {
		"id": 7,
	    "event_id": 7,
		"status": "active",
	    "date": "20220629",
		"venue": "Longhorn Cafe",
		"address": "1003 Rittiman Rd, San Antonio, TX 78218",
		"map_url": "https://goo.gl/maps/3WWg1pXmNQA2"
		},
	  {
	    "id": 8,
	    "event_id": 8,
		"status": "active",
	    "date": "20220713",
		"venue": "Longhorn Cafe",
		"address": "1003 Rittiman Rd, San Antonio, TX 78218",
		"map_url": "https://goo.gl/maps/3WWg1pXmNQA2"
	  },
	  {
	    "id": 9,
	    "event_id": 9,
		"status": "active",
	    "date": "20220727",
		"venue": "Longhorn Cafe",
		"address": "1003 Rittiman Rd, San Antonio, TX 78218",
		"map_url": "https://goo.gl/maps/3WWg1pXmNQA2"
	  },
	  {
	    "id": 10,
	    "event_id": 10,
		"status": "active",
	    "date": "20221028",
		"venue": "Longhorn Cafe",
		"address": "1003 Rittiman Rd, San Antonio, TX 78218",
		"map_url": "https://goo.gl/maps/3WWg1pXmNQA2"
	  },
	  {
	    "id": 11,
	    "event_id": 10,
		"status": "active",
	    "date": "20221116",
		"venue": "Longhorn Cafe",
		"address": "1003 Rittiman Rd, San Antonio, TX 78218",
		"map_url": "https://goo.gl/maps/3WWg1pXmNQA2"
	  },
	  {
	    "id": 12,
	    "event_id": 11,
		"status": "active",
	    "date": "20221214",
		"venue": "Longhorn Cafe",
		"address": "1003 Rittiman Rd, San Antonio, TX 78218",
		"map_url": "https://goo.gl/maps/3WWg1pXmNQA2"
	  }
	],
	"schools": [
	  {
	    "id": 1,
	    "site_host": "SASCA",
	    "in_event": true,
	    "event_id": 0,
	    "date": "2022",
	    "registration_link": "",
	    "venue": ""
	  },
	  {
	    "id": 2,
	    "site_host": "SASCA",
	    "in_event": true
	  }
	]
}
